arcgispro_ai/__init__.py
arcgispro_ai/toolboxes/arcgispro_ai_tools.pyt
arcgispro_ai/toolboxes/arcgispro_ai/__init__.py
arcgispro_ai/toolboxes/arcgispro_ai/arcgispro_ai_utils.py
arcgispro_ai/toolboxes/arcgispro_ai/run_tests.py
arcgispro_ai/toolboxes/arcgispro_ai/test_arcgispro_ai_utils.py
arcgispro_ai/toolboxes/arcgispro_ai/core/__init__.py
arcgispro_ai/toolboxes/arcgispro_ai/core/api_clients.py
arcgispro_ai/toolboxes/arcgispro_ai/core/test_api_clients.py
arcgispro_ai-0.0.19.dist-info/licenses/LICENSE
arcgispro_ai-0.0.19.dist-info/WHEEL
arcgispro_ai-0.0.19.dist-info/METADATA
arcgispro_ai-0.0.19.dist-info/RECORD
