Metadata-Version: 2.4
Name: arcgispro_ai
Version: 0.0.19
Summary: ArcGIS Pro AI Tools
Author-email: Danny McVey <dannybmcvey@gmail.com>
License-Expression: MIT
License-File: LICENSE
Project-URL: Home, https://github.com/danmaps/arcgispro_ai
